torchPIV/ControlsWidgets.py
torchPIV/PIVbackend.py
torchPIV/PIVwidgets.py
torchPIV/PlotterFunctions.py
torchPIV/__init__.py
torchPIV/mainWindow.py
torchPIV/settings.json
torchPIV/watchman.py
torchPIV/workers.py
TorchPIV-0.1.17.dist-info/LICENCE.txt
TorchPIV-0.1.17.dist-info/METADATA
TorchPIV-0.1.17.dist-info/WHEEL
TorchPIV-0.1.17.dist-info/top_level.txt
TorchPIV-0.1.17.dist-info/RECORD
