Metadata-Version: 2.1
Name: TorchPIV
Version: 0.1.17
Summary: Package for PIV data analysis
Home-page: https://github.com/NikNazarov/TorchPIV
Author: Nikita Nazarov
Author-email: nazarov.nik.an@gmail.com
Project-URL: Bug Tracker, https://github.com/NikNazarov/TorchPIV/issues
Classifier: Programming Language :: Python :: 3
Classifier: License :: OSI Approved :: MIT License
Classifier: Operating System :: OS Independent
Requires-Python: >=3.9
License-File: LICENCE.txt
Requires-Dist: matplotlib
Requires-Dist: numpy ==1.26.3
Requires-Dist: imageio ==2.33.1
Requires-Dist: opencv-python
Requires-Dist: pandas
Requires-Dist: PyQt5
Requires-Dist: scipy
Requires-Dist: watchdog
Requires-Dist: torch
